CSE 3108/verilog/adder1bit/main.v
module main (
    input A,
    input B,
    input Cin,
    output S,
    output Cout
);
assign S = A ^ B ^ Cin;
assign Cout = (A & B) | (B & Cin) | (A & Cin);
    
endmodule

CSE 3108/verilog/adder1bit/adder1bit_tb.v
module adder1bit_tb;

reg A, B, Cin;
wire S, Cout;
main uut (
    .A(A),
    .B(B),
    .Cin(Cin),
    .S(S),
    .Cout(Cout)
);
initial begin
    $monitor("Time=%0t, A=%b, B=%b, Cin=%b, S=%b, Cout=%b", $time, A, B, Cin, S, Cout);
    $dumpfile("adder1bit_tb.vcd");
    $dumpvars(0, adder1bit_tb);
    #10 A = 0; B = 0; Cin = 0;
    #10 A = 0; B = 0; Cin = 1;
    #10 A = 0; B = 1; Cin = 0;
    #10 A = 0; B = 1; Cin = 1;
    #10 A = 1; B = 0; Cin = 0;
    #10 A = 1; B = 0; Cin = 1;
    #10 A = 1; B = 1; Cin = 0;
    #10 A = 1; B = 1; Cin = 1;
    #10 $finish;
end

endmodule

CSE 3108/verilog/adder1bit/adder1bit_tb.vcd
$date
	Sat May 04 12:11:58 2024
$end
$version
	Icarus Verilog
$end
$timescale
	1s
$end
$scope module adder1bit_tb $end
$var wire 1 ! S $end
$var wire 1 " Cout $end
$var reg 1 # A $end
$var reg 1 $ B $end
$var reg 1 % Cin $end
$scope module uut $end
$var wire 1 # A $end
$var wire 1 $ B $end
$var wire 1 % Cin $end
$var wire 1 " Cout $end
$var wire 1 ! S $end
$upscope $end
$upscope $end
$enddefinitions $end
$comment Show the parameter values. $end
$dumpall
$end
#0
$dumpvars
x%
x$
x#
x"
x!
$end
#10
0"
0!
0%
0$
0#
#20
1!
1%
#30
0%
1$
#40
1"
0!
1%
#50
0"
1!
0%
0$
1#
#60
1"
0!
1%
#70
0%
1$
#80
1!
1%
